LICENSE
README.md
setup.py
NlpToolkit_Sampling.egg-info/PKG-INFO
NlpToolkit_Sampling.egg-info/SOURCES.txt
NlpToolkit_Sampling.egg-info/dependency_links.txt
NlpToolkit_Sampling.egg-info/top_level.txt
Sampling/Bootstrap.py
Sampling/CrossValidation.py
Sampling/KFoldCrossValidation.py
Sampling/StratifiedKFoldCrossValidation.py
Sampling/__init__.py