Metadata-Version: 2.1
Name: NlpToolkit-Sampling
Version: 1.0.6
Summary: Data sampling library
Home-page: https://github.com/StarlangSoftware/Sampling-Py
Author: olcaytaner
Author-email: olcay.yildiz@ozyegin.edu.tr
License: UNKNOWN
Platform: UNKNOWN
License-File: LICENSE
